Metadata-Version: 1.1
Name: chatbotentities
Version: 0.0.4
Summary: Chatbot Entities Extractor.
Home-page: https://github.com/kverdecia/chatbotentities
Author: Karel Antonio Verdecia Ortiz
Author-email: kverdecia@gmail.com
License: BSD
Download-URL: https://github.com/kverdecia/chatbotentities/tarball/0.0.4
Platform: UNKNOWN
Classifier: Development Status :: 3 - Alpha
Classifier: Intended Audience :: Developers
Classifier: Programming Language :: Python :: 3
